aiogram_part/__init__.py
aiogram_part/cli.py
aiogram_part/commands/__init__.py
aiogram_part/commands/check.py
aiogram_part/commands/database.py
aiogram_part/commands/deploy.py
aiogram_part/commands/enum.py
aiogram_part/commands/filter.py
aiogram_part/commands/handler.py
aiogram_part/commands/i18n.py
aiogram_part/commands/init.py
aiogram_part/commands/keyboard.py
aiogram_part/commands/middleware.py
aiogram_part/commands/model.py
aiogram_part/commands/service.py
aiogram_part/commands/state.py
aiogram_part/commands/stats.py
aiogram_part/commands/test.py
aiogram_part/commands/validator.py
aiogram_part/commands/webhook.py
aiogram_part/templates/__init__.py
aiogram_part/templates/enums.py
aiogram_part/templates/filters.py
aiogram_part/templates/handlers.py
aiogram_part/templates/i18n.py
aiogram_part/templates/keyboards.py
aiogram_part/templates/middlewares.py
aiogram_part/templates/models.py
aiogram_part/templates/project.py
aiogram_part/templates/services.py
aiogram_part/templates/states.py
aiogram_part/templates/tests.py
aiogram_part/templates/validators.py
aiogram_part/utils/__init__.py
aiogram_part/utils/file_manager.py
aiogram_part/utils/logger.py
aiogram_part-1.0.1.dist-info/licenses/LICENSE
aiogram_part-1.0.1.dist-info/METADATA
aiogram_part-1.0.1.dist-info/WHEEL
aiogram_part-1.0.1.dist-info/entry_points.txt
aiogram_part-1.0.1.dist-info/top_level.txt
aiogram_part-1.0.1.dist-info/RECORD
