Metadata-Version: 2.4
Name: aiogram-part
Version: 1.0.1
Summary: Professional CLI scaffolding tool for aiogram 3.x Telegram bots
Author-email: Sattorbek <sattorpro@gmail.com>
License: MIT
Project-URL: Homepage, https://github.com/sattorproduction/aiogram-part
Project-URL: Documentation, https://github.com/sattorproduction/aiogram-part#readme
Project-URL: Repository, https://github.com/sattorproduction/aiogram-part
Project-URL: Issues, https://github.com/sattorproduction/aiogram-part/issues
Keywords: aiogram,telegram,bot,cli,scaffolding,generator
Classifier: Development Status :: 5 - Production/Stable
Classifier: Intended Audience :: Developers
Classifier: License :: OSI Approved :: MIT License
Classifier: Programming Language :: Python :: 3
Classifier: Programming Language :: Python :: 3.10
Classifier: Programming Language :: Python :: 3.11
Classifier: Programming Language :: Python :: 3.12
Classifier: Topic :: Software Development :: Code Generators
Classifier: Topic :: Software Development :: Libraries :: Application Frameworks
Requires-Python: >=3.10
License-File: LICENSE
Requires-Dist: click>=8.1.0
Requires-Dist: rich>=13.0.0
Provides-Extra: dev
Requires-Dist: pytest>=7.0.0; extra == "dev"
Requires-Dist: black>=23.0.0; extra == "dev"
Requires-Dist: ruff>=0.1.0; extra == "dev"
Dynamic: license-file
